radyno/__init__.py
radyno/utils/__init__.py
radyno/utils/beam_utils.py
radyno/utils/beamline_utils.py
radyno/utils/fields_utils.py
radyno/utils/rad_utils.py
radyno/utils/segment_utils.py
radyno-0.0.13.dist-info/METADATA
radyno-0.0.13.dist-info/WHEEL
radyno-0.0.13.dist-info/top_level.txt
radyno-0.0.13.dist-info/RECORD
